finance_analyzer/__init__.py
finance_analyzer/analyzer.py
finance_analyzer12-0.1.4.dist-info/METADATA
finance_analyzer12-0.1.4.dist-info/WHEEL
finance_analyzer12-0.1.4.dist-info/top_level.txt
finance_analyzer12-0.1.4.dist-info/RECORD
