Metadata-Version: 2.1
Name: finance-analyzer12
Version: 0.1.4
Summary: Пакет для анализа финансовых транзакций.
Author-email: Nikita1207 <dorogin345@gmail.com>
Requires-Dist: pandas
